[
  {
    "satellite": "Eutelsat 7A/7B/7C @ 7.0°E",
    "frequency": "10962 H 9875",
    "id": "NOR-044 - SERVICE FEED 1",
    "key": "5A 52 26 D2 8F 28 9B 52"
  },
  {
    "satellite": "Eutelsat 7A/7B/7C @ 7.0°E",
    "frequency": "11001 H 14400",
    "id": "NOR-044 - EUROPE X NON VBR",
    "key": "00 09 CE D7 F4 7A E7 55"
  },
  {
    "satellite": "Eutelsat 7A/7B/7C @ 7.0°E",
    "frequency": "11014 H 7200",
    "id": "GVA_Fi01",
    "key": "DF 49 5C 84 19 D2 C6 B1"
  },
  {
    "satellite": "Eutelsat 7A/7B/7C @ 7.0°E",
    "frequency": "11045 V 9875",
    "id": "ITA548  W Feed B Com Main",
    "key": "DF 49 5C 84 19 D2 C6 B1"
  },
  {
    "satellite": "Eutelsat 7A/7B/7C @ 7.0°E",
    "frequency": "11057 V 9875",
    "id": "ITA548  W Feed A Std Main",
    "key": "DF 49 5C 84 19 D2 C6 B1"
  },
  {
    "satellite": "Eutelsat 7A/7B/7C @ 7.0°E",
    "frequency": "11084 V 15000",
    "id": "World Backup",
    "key": "AB 51 D4 D0 CA A6 41 B1"
  },
  {
    "satellite": "Eutelsat 7A/7B/7C @ 7.0°E",
    "frequency": "11089 H 7200",
    "id": "EUROLEAGUE FINAL 4_DAY 2- ATH. MAIN",
    "key": "F4 22 21 37 70 3B 1C C7"
  },
  {
    "satellite": "Eutelsat 7A/7B/7C @ 7.0°E",
    "frequency": "11102 V 15000",
    "id": "DAZN-backup_01",
    "key": "AB 51 D2 CE 4C AA 61 57"
  },
  {
    "satellite": "Eutelsat 7A/7B/7C @ 7.0°E",
    "frequency": "11505 V 7200",
    "id": "E393 P1 CLEAN",
    "key": "CD DA 45 EC 45 88 99 66"
  },
  {
    "satellite": "Eutelsat 7A/7B/7C @ 7.0°E",
    "frequency": "11514 V 7200",
    "id": "E393 P3 DIRTY MAIN",
    "key": "AB 87 66 98 78 98 98 A8"
  },
  {
    "satellite": "Eutelsat 7A/7B/7C @ 7.0°E",
    "frequency": "11523 V 7120",
    "id": "EDM HD ENC-1",
    "key": "B2 C5 D3 4A E6 F4 A7 81"
  },
  {
    "satellite": "Eutelsat 7A/7B/7C @ 7.0°E",
    "frequency": "12548 H 9875",
    "id": "ERC Service Park Main",
    "key": "27 43 FD 67 32 08 5C 96"
  },
  {
    "satellite": "Eutelsat 7A/7B/7C @ 7.0°E",
    "frequency": "12577 H 7500",
    "id": "NLFLEV_HOL-090 CH-A",
    "key": "11 A8 CB 84 DA 65 4A 89"
  },
  {
    "satellite": "Eutelsat 7A/7B/7C @ 7.0°E",
    "frequency": "12602 V 7200",
    "id": "Polsat Sport",
    "key": "20 26 AB F1 CD 1E CA B5"
  },
  {
    "satellite": "Eutelsat 7A/7B/7C @ 7.0°E",
    "frequency": "12736 V 7200",
    "id": "ITA 415 MAIN",
    "key": "20 26 05 4B AA E7 9A 2B"
  },
  {
    "satellite": "Eutelsat Hotbird 13B/13C/13G @ 13.0°E",
    "frequency": "10815 H 9700",
    "id": "IIHF2026 - FRI - VO TIP",
    "key": "09 29 00 32 A1 3F 03 E3"
  },
  {
    "satellite": "Eutelsat Hotbird 13B/13C/13G @ 13.0°E",
    "frequency": "11592 H 9600",
    "id": "NLEMG HOL270-1",
    "key": "09 29 00 32 A1 3F 03 E3"
  },
  {
    "satellite": "Eutelsat Hotbird 13B/13C/13G @ 13.0°E",
    "frequency": "12585 V 9700",
    "id": "IIHF2026 - ZUR - WF",
    "key": "01 FC 10 0D 0C 12 2C 4A"
  },
  {
    "satellite": "Eutelsat Hotbird 13B/13C/13G @ 13.0°E",
    "frequency": "12597 V 9700",
    "id": "IIHF2026 - ZUR - VO GER",
    "key": "6A AC 90 A6 47 4B 28 BA"
  }
]