[
    {
        "satellite": "Eutelsat 7A/7B/7C  7.0E",
        "frequency": "11071 H 7200",
        "id": "IMG A EU",
        "key": "6F 77 E4 CA 2E FC 44 6E"
    },
    {
        "satellite": "Eutelsat 7A/7B/7C  7.0E",
        "frequency": "12634 V 17140",
        "id": "",
        "key": "AA 12 BB 77 11 22 34 67"
    },
    {
        "satellite": "Eutelsat 7A/7B/7C  7.0E",
        "frequency": "11102 V 17140",
        "id": "C Chelsea v PSG",
        "key": "BB AA 85 EA 46 CA BA CA"
    },
    {
        "satellite": "Eutelsat 7A/7B/7C  7.0E",
        "frequency": "11013 H 4830",
        "id": "Unname",
        "key": "A1 E1 F6 78 90 2E DE 9C"
    },
    {
        "satellite": "Eutelsat 7A/7B/7C  7.0E",
        "frequency": "12728 V 7200",
        "id": "OB-09 A",
        "key": "4E 5B 29 D2 6D D1 9A D8"
    },
    {
        "satellite": "Eutelsat 16A  16.0E",
        "frequency": "10977 V 4800",
        "id": "pol-053_enc2",
        "key": "AB BA 26 8B DC AE 03 8D"
    },
    {
        "satellite": "Eutelsat 16A  16.0E",
        "frequency": "10962 H 3333",
        "id": "DEFAULT",
        "key": "AA CD 33 AA 27 CB AB 9D"
    },
    {
        "satellite": "Eutelsat 7A/7B/7C  7.0E",
        "frequency": "11180 H 7200",
        "id": "FIBA WOMENS CYP vs POL_MAIN",
        "key": "E2 31 21 34 D3 BA 8B 18"
    },
    {
        "satellite": "Eutelsat 7A/7B/7C  7.0E",
        "frequency": "11023 V 7200",
        "id": "SNG 02 - Chain A",
        "key": "82 4E D4 A4 16 88 DA 78"
    },
    {
        "satellite": "Eutelsat 7A/7B/7C  7.0E",
        "frequency": "11014 V 7200",
        "id": "SNG 05 - CHAIN B",
        "key": "9D E9 75 FB EF 20 93 A2"
    },
    {
        "satellite": "Eutelsat 7A/7B/7C  7.0E",
        "frequency": "12705 V 7200",
        "id": "TUR 141",
        "key": "C9 FE 79 40 11 62 CA 3D"
    }
]