[
    {
        "satellite": "Eutelsat 16A @ 16.0°E",
        "frequency": "10977 V 4800",
        "id": "POL138_A",
        "key": "AB BA 26 8B DC AE 06 90"
    },
    {
        "satellite": "Eutelsat 7A/7B/7C @ 7.0°E",
        "frequency": "11018 H 14400",
        "id": "GVA_Fi07",
        "key": "04 F8 B6 B2 AC 8F 06 41"
    },
    {
        "satellite": "Eutelsat 7A/7B/7C @ 7.0°E",
        "frequency": "11070 V 7200",
        "id": "Fi02_ACB",
        "key": "EE B5 E8 8B F0 DA CA 94"
    },
    {
        "satellite": "Eutelsat 10A @ 10.0°E",
        "frequency": "10721 H 7200",
        "id": "Encoder 1",
        "key": "C4 5A F1 0F AE BD 39 A4"
    },
    {
        "satellite": "Eutelsat 7A/7B/7C @ 7.0°E",
        "frequency": "10977 V 7200",
        "id": "ITA-274 World Feed",
        "key": "FB 65 D0 30 60 4E 65 13"
    },
    {
        "satellite": "Eutelsat 7A/7B/7C @ 7.0°E",
        "frequency": "10964 V 14400",
        "id": "ITA 274 Feed C MAIN",
        "key": "FA 65 D0 2F 60 4E 65 13"
    },
    {
        "satellite": "Eutelsat Hotbird 13B/13C/13G @ 13.0°E",
        "frequency": "10830 V 7500",
        "id": "TUR139-Main",
        "key": "1F CB B1 9B F4 C9 C1 7E"
    },
    {
        "satellite": "Eutelsat 7A/7B/7C @ 7.0°E",
        "frequency": "12574 H 9600",
        "id": "SUI 066 A",
        "key": "B8 0D 7C 41 8E F9 5E E5"
    },
    {
        "satellite": "Eutelsat 7A/7B/7C @ 7.0°E",
        "frequency": "11106 V 7200",
        "id": "Fi20_GNVE",
        "key": "4D 01 D9 27 5D 45 DF 81"
    },
    {
        "satellite": "Eutelsat 7A/7B/7C @ 7.0°E",
        "frequency": "11012 H 4938",
        "id": "ORA - ANA",
        "key": "9D 8C 7B A4 6A 5E 8B 53"
    },
    {
        "satellite": "Eutelsat 7A/7B/7C @ 7.0°E",
        "frequency": "11606 V 7500",
        "id": "ABBA",
        "key": "AB BA 20 85 25 20 26 6B"
    },
    {
        "satellite": "Eutelsat 7A/7B/7C @ 7.0°E",
        "frequency": "12510 V 7200",
        "id": "EMF",
        "key": "AE 25 BE 91 35 EC 11 32"
    }
]