[
    {
        "satellite": "Eutelsat 10A @ 10.0°E",
        "frequency": "11291 H 7200",
        "id": "URG 019",
        "key": "20 26 F6 3C F1 DB BA 86"
    },
    {
        "satellite": "Eutelsat 7A/7B/7C @ 7.0°E",
        "frequency": "12638 V 7120",
        "id": "ITA727 Enc2",
        "key": "32 99 FA C5 EE 12 15 15"
    },
    {
        "satellite": "Eutelsat 7A/7B/7C @ 7.0°E",
        "frequency": "10978 V 7200",
        "id": "UWW-TIRANA",
        "key": "E4 73 51 A8 37 8E AB 70"
    },
    {
        "satellite": "Eutelsat 7A/7B/7C @ 7.0°E",
        "frequency": "12647 V 7120",
        "id": "Gallagher PREM - Northampton Saints v Bath Rugby",
        "key": "11 CC 45 22 54 AA 11 0F"
    },
    {
        "satellite": "Eutelsat 7A/7B/7C @ 7.0°E",
        "frequency": "11018 H 14400",
        "id": "GVA_Fi07",
        "key": "3C E4 F5 15 B0 EA 50 EA"
    },
    {
        "satellite": "Eutelsat 7A/7B/7C @ 7.0°E",
        "frequency": "11057 V 9875",
        "id": "GVA_Fi05 LFP 5",
        "key": "FA B7 DB 8C 61 37 13 AB"
    },
    {
        "satellite": "Eutelsat 7A/7B/7C @ 7.0°E",
        "frequency": "12696 V 7500",
        "id": "LPGA - The Chevron Championship",
        "key": "89 5C 64 49 A8 16 4C 0A"
    },
    {
        "satellite": "Eutelsat 10A @ 10.0°E",
        "frequency": "10732 V 34000",
        "id": "SUPPONOR MENA 1",
        "key": "F7 5F 18 6E 94 2E 5A 1C"
    },
    {
        "satellite": "Eutelsat 10A @ 10.0°E",
        "frequency": "10732 V 34000",
        "id": "SUPPONOR AFRICA 1",
        "key": "B0 61 07 18 E9 DB 98 5C"
    },
    {
        "satellite": "Eutelsat 10A @ 10.0°E",
        "frequency": "10732 V 34000",
        "id": "OVERON 2",
        "key": "9F 9C 3C 77 A5 D7 77 F3"
    },
    {
        "satellite": "Eutelsat 10A @ 10.0°E",
        "frequency": "10732 V 34000",
        "id": "OVERON 1",
        "key": "02 00 5E 60 5E 0F C8 35"
    },
    {
        "satellite": "Eutelsat 16A @ 16.0°E",
        "frequency": "11012 V 4938",
        "id": "YSM-013M",
        "key": "AB BA 20 85 25 20 26 6B"
    },
    {
        "satellite": "Eutelsat 7A/7B/7C @ 7.0°E",
        "frequency": "10996 H 7200",
        "id": "Pitch Pre Match Man C V Southampton",
        "key": "12 34 AC F2 FB 87 65 E7"
    },
    {
        "satellite": "Eutelsat 7A/7B/7C @ 7.0°E",
        "frequency": "10969 V 7200",
        "id": "F-509/fleury-MAIN",
        "key": "E9 33 32 4E 56 18 EB 59"
    },
    {
        "satellite": "Eutelsat 7A/7B/7C @ 7.0°E",
        "frequency": "11580 V 7200",
        "id": "NLEMG HOL312-1",
        "key": "12 3A BC 08 45 6D EF A1"
    },
    {
        "satellite": "Eutelsat 7A/7B/7C @ 7.0°E",
        "frequency": "12678 H 7200",
        "id": "E399 BACK",
        "key": "A0 D1 3A AB A6 43 42 2B"
    }
]