[
    {
        "satellite": "Eutelsat 7A/7B/7C  7.0E",
        "frequency": "12647 V 7200",
        "id": "Fi17GNVE",
        "key": "DD 9E 2C A7 09 1F 0E 36"
    },
    {
        "satellite": "Eutelsat 10A  10.0E",
        "frequency": "11265 H 7200",
        "id": "LNR UK PROVENCE VS COLOMIERS PRO D2",
        "key": "F5 76 26 91 03 26 F2 1B"
    },
    {
        "satellite": "Eutelsat Hotbird 13B/13C/13G  13.0E",
        "frequency": "12611 V 7200",
        "id": "GCUK Enc 1",
        "key": "FD DC 20 F9 26 DC FD FF"
    },
    {
        "satellite": "Eutelsat Hotbird 13B/13C/13G  13.0E",
        "frequency": "12592 V 7200",
        "id": "GCUK Enc 2",
        "key": "23 01 71 95 96 52 0A F2"
    },
    {
        "satellite": "Eutelsat 16A  16.0E",
        "frequency": "10985 V 9600",
        "id": "POL-90a",
        "key": "AB BA 26 8B DC AE 03 8D"
    },
    {
        "satellite": "Eutelsat 16A  16.0E",
        "frequency": "10962 H 3333",
        "id": "DEFAULT",
        "key": "AA CD 33 AA 27 CB AB 9D"
    },
    {
        "satellite": "Eutelsat 10A  10.0E",
        "frequency": "11273 H 7200",
        "id": "POL-100   MAIN",
        "key": "E5 0F F7 EB 9D 03 26 C6"
    }
]