[
    {
        "key": "AB BA 26 8B DC AE 03 8D",
        "satellite": "Eutelsat 16A @ 16.0E",
        "frequency": "10974 V 9600",
        "id": "pol-053_enc2"
    },
    {
        "key": "B1 76 34 5B 3A 22 4C A8",
        "satellite": "Eutelsat 7A/7B/7C @ 7.0E",
        "frequency": "11601 V 15000",
        "id": "ZUFFA"
    },
    {
        "key": "FD A2 A8 47 0A 3C E2 28",
        "satellite": "Eutelsat 10A @ 10.0E",
        "frequency": "10731 V 34000",
        "id": "OVERON 1"
    },
    {
        "key": "F0 22 F2 04 F9 EA 5B 3E",
        "satellite": "Eutelsat 10A @ 10.0E",
        "frequency": "10731 V 34000",
        "id": "LIGA HYPERMOTION 1"
    },
    {
        "key": "B9 E3 94 30 D8 13 49 34",
        "satellite": "Eutelsat 7A/7B/7C @ 7.0E",
        "frequency": "11070 H 7200",
        "id": "IMG A EU"
    },
    {
        "key": "8B DD EA 52 40 16 02 58",
        "satellite": "Eutelsat 7A/7B/7C @ 7.0E",
        "frequency": "11053 V 7200",
        "id": "TBS ADHOC ENC 6"
    },
    {
        "key": "43 7A 11 CE 13 EB C3 C1",
        "satellite": "Eutelsat 7A/7B/7C @ 7.0E",
        "frequency": "11044 V 7200",
        "id": "TBS ADHOC ENC 3"
    },
    {
        "key": "77 93 52 5C 99 08 86 27",
        "satellite": "Eutelsat 16A @ 16.0E",
        "frequency": "11073 H 7500",
        "id": "POL070 TVN24 POZ"
    },
    {
        "key": "AA BB 20 85 26 03 AC D5",
        "satellite": "Eutelsat 7A/7B/7C @ 7.0E",
        "frequency": "11062 H 7500",
        "id": "WBC Korea v Australia"
    },
    {
        "key": "AB CD EE 66 FF 09 03 0B",
        "satellite": "Eutelsat 7A/7B/7C @ 7.0E",
        "frequency": "11189 H 7200",
        "id": "Encoder 2"
    }
]